[
  {
    "id": "L0-project-overview",
    "level": "L0_project",
    "title": "Orca 项目总览",
    "parent": null,
    "status": "done",
    "depends_on": [],
    "sources": [
      "README.md",
      "package.json",
      "electron.vite.config.ts",
      "AGENTS.md",
      "src/main/index.ts",
      "src/main/persistence.ts",
      "src/main/sqlite/sync-database.ts",
      "src/renderer/src/main.tsx",
      "src/renderer/src/App.tsx",
      "src/preload/index.ts",
      "src/cli/index.ts",
      "src/relay/relay.ts",
      "mobile/README.md"
    ],
    "discovered_from": "user-objective",
    "topic_dir": "teach/open-ai-desktop/orca/00-overview",
    "output_path": "teach/open-ai-desktop/orca/00-overview/lessons/0001-project-map.html",
    "required_outputs": {
      "meta": [
        "teach/open-ai-desktop/orca/00-overview/MISSION.md",
        "teach/open-ai-desktop/orca/00-overview/RESOURCES.md",
        "teach/open-ai-desktop/orca/00-overview/SNAPSHOT.md"
      ],
      "lessons": [
        "teach/open-ai-desktop/orca/00-overview/lessons/0001-project-map.html"
      ],
      "reference": [
        "teach/open-ai-desktop/orca/00-overview/reference/00-overview.html"
      ]
    },
    "lesson_manifest": [
      {
        "path": "teach/open-ai-desktop/orca/00-overview/lessons/0001-project-map.html",
        "objective": "15 分钟建立 Orca 的全局架构地图",
        "estimated_minutes": 15
      }
    ],
    "new_goals_found": [
      "L1-main-runtime",
      "L1-main-ipc",
      "L1-renderer-shell",
      "L1-cli-relay",
      "L1-mobile-companion",
      "L1-shared-contracts",
      "L2-worktree-create-flow",
      "L2-ssh-relay-session-flow",
      "L2-orca-cli-command-flow",
      "L2-mobile-pairing-flow",
      "L4-relay-reconnect"
    ],
    "retry_count": 2,
    "completed_at": "2026-07-07T17:13:29+08:00",
    "review_status": "conditional_pass",
    "review_issues": {
      "critical": [],
      "important": [
        {
          "location": "reference/00-overview.html 技术栈全景",
          "description": "初版缺少持久化/数据库层说明。",
          "resolution": "已补充 orca-data.json、safeStorage 与 src/main/sqlite/sync-database.ts；重新生成 SNAPSHOT 并通过 audit_topic.py。"
        }
      ],
      "minor": [
        {
          "location": "lessons/0001-project-map.html 结尾",
          "description": "初版缺少课后主来源和追问提醒。",
          "resolution": "已补充 README、L0 参考文档和后续追问方向。"
        }
      ]
    },
    "review_round": 1
  },
  {
    "id": "L1-main-runtime",
    "level": "L1_module",
    "title": "主进程 Runtime 与 Daemon 模块",
    "parent": "L0-project-overview",
    "status": "done",
    "depends_on": [
      "L0-project-overview"
    ],
    "sources": [
      "src/main/runtime/orca-runtime.ts",
      "src/main/runtime/runtime-rpc.ts",
      "src/main/runtime/mobile-pairing-files.ts",
      "src/main/daemon/daemon-init.ts",
      "src/main/daemon/daemon-entry.ts"
    ],
    "discovered_from": "L0-project-overview",
    "topic_dir": "teach/open-ai-desktop/orca/module-main-runtime",
    "output_path": "teach/open-ai-desktop/orca/module-main-runtime/lessons/0001-main-runtime-module-tour.html",
    "required_outputs": {
      "meta": [
        "teach/open-ai-desktop/orca/module-main-runtime/MISSION.md",
        "teach/open-ai-desktop/orca/module-main-runtime/RESOURCES.md",
        "teach/open-ai-desktop/orca/module-main-runtime/SNAPSHOT.md"
      ],
      "lessons": [
        "teach/open-ai-desktop/orca/module-main-runtime/lessons/0001-main-runtime-module-tour.html"
      ],
      "reference": [
        "teach/open-ai-desktop/orca/module-main-runtime/reference/main-runtime-overview.html"
      ]
    },
    "lesson_manifest": [
      {
        "path": "teach/open-ai-desktop/orca/module-main-runtime/lessons/0001-main-runtime-module-tour.html",
        "objective": "15 分钟内判断一段主进程代码属于状态层、控制面传输层，还是长期 PTY 宿主层",
        "estimated_minutes": 15
      }
    ],
    "new_goals_found": [
      "L2-worktree-create-flow",
      "L2-mobile-pairing-flow",
      "L2-ssh-relay-session-flow"
    ],
    "retry_count": 1,
    "completed_at": "2026-07-07T17:58:46+08:00",
    "review_status": "conditional_pass",
    "review_issues": {
      "critical": [],
      "important": [
        {
          "location": "00-index.md 与 _progress 台账",
          "description": "初审时 module-main-runtime 已生成，但总导航和进度台账仍标为待生成。",
          "resolution": "已同步 00-index.md、_progress.md 和 _progress.json，L1 统计更新为 3/6。"
        },
        {
          "location": "lessons/0001-main-runtime-module-tour.html 文件树",
          "description": "初版文件树列出 6 个源码文件，严格按短课合约看超过 3 个源码文件。",
          "resolution": "已压缩为 index.ts、runtime-rpc.ts、daemon-init.ts 三个代表源码文件；orca-runtime.ts 等细节移到参考页。"
        }
      ],
      "minor": [
        {
          "location": "SNAPSHOT.md 源文件引用",
          "description": "初版快照将 userData 文件名误识别为源码引用，且部分短文件名未带完整路径。",
          "resolution": "已改写参考页中的源码路径与 userData 文件描述，并重新生成 SNAPSHOT.md。"
        },
        {
          "location": "lessons/0001-main-runtime-module-tour.html 装配顺序说明",
          "description": "初版可能让读者误解 daemon 初始化严格先于 runtimeRpc.start() 完成。",
          "resolution": "已补充说明 daemon 初始化是 first-window startup service 的异步工作。"
        }
      ]
    },
    "review_round": 1
  },
  {
    "id": "L1-main-ipc",
    "level": "L1_module",
    "title": "主进程 IPC 边界模块",
    "parent": "L0-project-overview",
    "status": "done",
    "depends_on": [
      "L0-project-overview"
    ],
    "sources": [
      "src/main/ipc/register-core-handlers.ts",
      "src/main/ipc/pty.ts",
      "src/main/ipc/filesystem.ts",
      "src/main/ipc/filesystem-watcher.ts",
      "src/main/ipc/mobile.ts",
      "src/preload/index.ts"
    ],
    "discovered_from": "L0-project-overview",
    "topic_dir": "teach/open-ai-desktop/orca/module-main-ipc",
    "output_path": "teach/open-ai-desktop/orca/module-main-ipc/lessons/0001-main-ipc-module-tour.html",
    "required_outputs": {
      "meta": [
        "teach/open-ai-desktop/orca/module-main-ipc/MISSION.md",
        "teach/open-ai-desktop/orca/module-main-ipc/RESOURCES.md",
        "teach/open-ai-desktop/orca/module-main-ipc/SNAPSHOT.md"
      ],
      "lessons": [
        "teach/open-ai-desktop/orca/module-main-ipc/lessons/0001-main-ipc-module-tour.html"
      ],
      "reference": [
        "teach/open-ai-desktop/orca/module-main-ipc/reference/main-ipc-overview.html"
      ]
    },
    "lesson_manifest": [
      {
        "path": "teach/open-ai-desktop/orca/module-main-ipc/lessons/0001-main-ipc-module-tour.html",
        "objective": "15 分钟内能从一个 renderer API 追到 preload channel 和 main handler",
        "estimated_minutes": 15
      }
    ],
    "new_goals_found": [
      "L2-worktree-create-flow"
    ],
    "retry_count": 1,
    "completed_at": "2026-07-07T18:12:57+08:00",
    "review_status": "conditional_pass",
    "review_issues": {
      "critical": [],
      "important": [
        {
          "location": "reference/main-ipc-overview.html 总注册职责",
          "description": "初版把 repo/worktree 误写成 registerCoreHandlers() 一次性注册范围。",
          "resolution": "已改为 registerCoreHandlers() 只列真实核心 domain handlers，并说明 repo/worktree handlers 属于窗口装配层。"
        },
        {
          "location": "reference/main-ipc-overview.html 文件与 Git 职责",
          "description": "初版把 filesystem watcher 归到 filesystem.ts。",
          "resolution": "已说明 watcher 由 src/main/ipc/filesystem-watcher.ts 通过 registerFilesystemWatcherHandlers() 单独注册。"
        }
      ],
      "minor": [
        {
          "location": "index.md 教学主题表",
          "description": "初版新增 module-main-ipc 时表格被空行分断。",
          "resolution": "已移除空行，保持 Markdown 表格连续渲染。"
        },
        {
          "location": "lessons/0001-main-ipc-module-tour.html 检索练习",
          "description": "短课练习答案额外引入 filesystem.ts，严格看可能超过 3 个源码文件。",
          "resolution": "已把具体 Git handler 文件路径移到参考页，lesson 只保留边界判断路径。"
        }
      ]
    },
    "review_round": 1
  },
  {
    "id": "L1-renderer-shell",
    "level": "L1_module",
    "title": "Renderer 应用壳与状态模块",
    "parent": "L0-project-overview",
    "status": "done",
    "depends_on": [
      "L0-project-overview"
    ],
    "sources": [
      "src/renderer/src/main.tsx",
      "src/renderer/src/App.tsx",
      "src/renderer/src/store/index.ts",
      "src/renderer/src/store/slices/tabs.ts",
      "src/renderer/src/runtime/sync-runtime-graph.ts",
      "src/renderer/src/hooks/useIpcEvents.ts",
      "src/renderer/src/hooks/useIpcEvents.test.ts",
      "src/renderer/src/runtime/sync-runtime-graph-scheduling.test.ts",
      "src/renderer/src/runtime/sync-runtime-graph.test.ts",
      "src/renderer/src/store/slices/tabs.test.ts",
      "src/renderer/src/store/slices/store-session-cascades.test.ts"
    ],
    "discovered_from": "L0-project-overview",
    "topic_dir": "teach/open-ai-desktop/orca/module-renderer-shell",
    "output_path": "teach/open-ai-desktop/orca/module-renderer-shell/lessons/0001-renderer-shell-module-tour.html",
    "required_outputs": {
      "meta": [
        "teach/open-ai-desktop/orca/module-renderer-shell/MISSION.md",
        "teach/open-ai-desktop/orca/module-renderer-shell/RESOURCES.md",
        "teach/open-ai-desktop/orca/module-renderer-shell/SNAPSHOT.md"
      ],
      "lessons": [
        "teach/open-ai-desktop/orca/module-renderer-shell/lessons/0001-renderer-shell-module-tour.html"
      ],
      "reference": [
        "teach/open-ai-desktop/orca/module-renderer-shell/reference/renderer-shell-overview.html"
      ]
    },
    "lesson_manifest": [
      {
        "path": "teach/open-ai-desktop/orca/module-renderer-shell/lessons/0001-renderer-shell-module-tour.html",
        "objective": "15 分钟内能说清 renderer 入口、App shell 和全局 store 的分工",
        "estimated_minutes": 15
      }
    ],
    "new_goals_found": [
      "L2-worktree-create-flow"
    ],
    "retry_count": 1,
    "completed_at": "2026-07-07T18:28:17+08:00",
    "review_status": "conditional_pass",
    "review_issues": {
      "critical": [],
      "important": [
        {
          "location": "reference/renderer-shell-overview.html 启动链路",
          "description": "初版把 settings、keybindings、UI、repos、project scope、worktrees 和 lineage 统称为并行读取，表述过宽。",
          "resolution": "已改为 settings 先串行读取，UI/keybindings/onboarding 提前发起，repos 完成后 project/folder scope 与 worktrees/lineage 扫描部分重叠。"
        },
        {
          "location": "lessons/0001-renderer-shell-module-tour.html session writer",
          "description": "初版“打开 session writer”容易让读者误解 writer 是水合成功后才创建。",
          "resolution": "已改为解锁 session writer 真正写回的门控，并在 NOTES 中说明 subscriber 可先创建但写入受 workspaceSessionReady 与 hydrationSucceeded 门控。"
        }
      ],
      "minor": [
        {
          "location": "RESOURCES.md 测试清单",
          "description": "初版资源清单漏列 useIpcEvents.test.ts。",
          "resolution": "已补充 src/renderer/src/hooks/useIpcEvents.test.ts，并重新生成 SNAPSHOT。"
        },
        {
          "location": "_progress.json sources",
          "description": "初版 L1-renderer-shell sources 只列核心实现文件，未列 useIpcEvents.ts 和测试文件。",
          "resolution": "已按 SNAPSHOT 补齐 useIpcEvents.ts 及相关测试文件，便于后续覆盖追踪。"
        }
      ]
    },
    "review_round": 1
  },
  {
    "id": "L1-cli-relay",
    "level": "L1_module",
    "title": "CLI 与远端 Relay 模块",
    "parent": "L0-project-overview",
    "status": "done",
    "depends_on": [
      "L0-project-overview"
    ],
    "sources": [
      "src/cli/index.ts",
      "src/cli/dispatch.ts",
      "src/cli/runtime-client.ts",
      "src/relay/relay.ts",
      "src/relay/dispatcher.ts",
      "src/relay/protocol.ts"
    ],
    "discovered_from": "L0-project-overview",
    "topic_dir": "teach/open-ai-desktop/orca/module-cli-relay",
    "output_path": "teach/open-ai-desktop/orca/module-cli-relay/lessons/0001-cli-relay-module-tour.html",
    "required_outputs": {
      "meta": [
        "teach/open-ai-desktop/orca/module-cli-relay/MISSION.md",
        "teach/open-ai-desktop/orca/module-cli-relay/RESOURCES.md",
        "teach/open-ai-desktop/orca/module-cli-relay/SNAPSHOT.md"
      ],
      "lessons": [
        "teach/open-ai-desktop/orca/module-cli-relay/lessons/0001-cli-relay-module-tour.html"
      ],
      "reference": [
        "teach/open-ai-desktop/orca/module-cli-relay/reference/cli-relay-overview.html"
      ]
    },
    "lesson_manifest": [
      {
        "path": "teach/open-ai-desktop/orca/module-cli-relay/lessons/0001-cli-relay-module-tour.html",
        "objective": "15 分钟理解 CLI 与 relay 的模块边界",
        "estimated_minutes": 15
      }
    ],
    "new_goals_found": [
      "L2-orca-cli-command-flow",
      "L2-ssh-relay-session-flow",
      "L4-relay-reconnect"
    ],
    "retry_count": 1,
    "completed_at": "2026-07-07T17:40:25+08:00",
    "review_status": "conditional_pass",
    "review_issues": {
      "critical": [],
      "important": [
        {
          "location": "lessons/0001-cli-relay-module-tour.html 文件树",
          "description": "初版使用 pre/code 展示文件树，不符合 TREE-FORMAT 的 filetree 容器要求。",
          "resolution": "已改为 <div class=\"filetree\"> 并重新生成 SNAPSHOT、通过 audit_topic.py。"
        },
        {
          "location": "reference/cli-relay-overview.html 关键依赖与调用示例",
          "description": "初版对 L1 关键依赖和简单调用示例表达不够显式。",
          "resolution": "已新增“关键依赖”和“简单调用示例”区块。"
        }
      ],
      "minor": [
        {
          "location": "HTML 正文",
          "description": "初版有少量 Markdown 反引号直接显示。",
          "resolution": "已替换为 <code>。"
        }
      ]
    },
    "review_round": 1
  },
  {
    "id": "L1-mobile-companion",
    "level": "L1_module",
    "title": "移动端 Companion 模块",
    "parent": "L0-project-overview",
    "status": "done",
    "depends_on": [
      "L0-project-overview"
    ],
    "sources": [
      "mobile/README.md",
      "mobile/app/_layout.tsx",
      "mobile/app/index.tsx",
      "mobile/app/pair.tsx",
      "mobile/app/pair-scan.tsx",
      "mobile/app/pair-confirm.tsx",
      "mobile/app/h/[hostId]/index.tsx",
      "mobile/app/h/[hostId]/session/[worktreeId].tsx",
      "mobile/src/transport/pairing.ts",
      "mobile/src/transport/host-store.ts",
      "mobile/src/transport/client-context.tsx",
      "mobile/src/transport/rpc-client.ts",
      "mobile/src/worktree/resume-worktree.ts",
      "mobile/src/transport/pairing.test.ts",
      "mobile/src/transport/pair-confirm-state.test.ts",
      "mobile/src/transport/pairing-connection-attempt.test.ts",
      "mobile/src/transport/rpc-client.test.ts",
      "mobile/src/transport/rpc-client-live-recovery.test.ts",
      "mobile/src/worktree/resume-worktree.test.ts"
    ],
    "discovered_from": "L0-project-overview",
    "topic_dir": "teach/open-ai-desktop/orca/module-mobile-companion",
    "output_path": "teach/open-ai-desktop/orca/module-mobile-companion/lessons/0001-mobile-companion-module-tour.html",
    "required_outputs": {
      "meta": [
        "teach/open-ai-desktop/orca/module-mobile-companion/MISSION.md",
        "teach/open-ai-desktop/orca/module-mobile-companion/RESOURCES.md",
        "teach/open-ai-desktop/orca/module-mobile-companion/SNAPSHOT.md"
      ],
      "lessons": [
        "teach/open-ai-desktop/orca/module-mobile-companion/lessons/0001-mobile-companion-module-tour.html"
      ],
      "reference": [
        "teach/open-ai-desktop/orca/module-mobile-companion/reference/mobile-companion-overview.html"
      ]
    },
    "lesson_manifest": [
      {
        "path": "teach/open-ai-desktop/orca/module-mobile-companion/lessons/0001-mobile-companion-module-tour.html",
        "objective": "15 分钟内能说清移动端入口、host 首页和 RPC client 的分工",
        "estimated_minutes": 15
      }
    ],
    "new_goals_found": [
      "L2-mobile-pairing-flow"
    ],
    "retry_count": 1,
    "completed_at": "2026-07-07T18:41:38+08:00",
    "review_status": "conditional_pass",
    "review_issues": {
      "critical": [],
      "important": [
        {
          "location": "_progress.json、_progress.md、00-index.md",
          "description": "初审时主题目录和 index.md 已生成，但项目级完成状态仍未同步。",
          "resolution": "已将 L1-mobile-companion 标记为 done，并同步总体进度、L1 统计和总导航。"
        },
        {
          "location": "SNAPSHOT.md 源文件覆盖",
          "description": "初版快照未记录 mobile/README.md、mobile/src/transport/pairing.ts 和 mobile/src/worktree/resume-worktree.ts 等核心来源。",
          "resolution": "已在参考页显式引用 README、pairing.ts、resume-worktree.ts 和 pair-scan.tsx，并重新生成 SNAPSHOT，引用源文件数更新为 19。"
        },
        {
          "location": "lessons/0001-mobile-companion-module-tour.html 与 reference/mobile-companion-overview.html Resume card",
          "description": "初版把首页外层 last visited 策略和 pickResumeWorktree() fallback helper 的测试覆盖混在一起描述。",
          "resolution": "已明确 last visited 属于 mobile/app/index.tsx 外层策略；resume-worktree.ts helper 只负责桌面 active、最近输出、第一项的 fallback。"
        }
      ],
      "minor": [
        {
          "location": "RESOURCES.md 与 reference/mobile-companion-overview.html pairing 入口",
          "description": "初版提到 QR scan 但未列 mobile/app/pair-scan.tsx。",
          "resolution": "已补充 pair-scan.tsx，并说明扫码 UI 细节留到 L2 mobile pairing flow。"
        },
        {
          "location": "reference/mobile-companion-overview.html 协议兼容说明",
          "description": "初版 mobile/README.md 中的 protocol compatibility、mock server 和调试说明只在资源清单出现。",
          "resolution": "已新增协议兼容与调试流程行，说明 status.get/protocol-version 兜底，细节归 shared/L2。"
        }
      ]
    },
    "review_round": 1
  },
  {
    "id": "L1-shared-contracts",
    "level": "L1_module",
    "title": "共享协议与类型模块",
    "parent": "L0-project-overview",
    "status": "done",
    "depends_on": [
      "L0-project-overview"
    ],
    "sources": [
      "src/shared/types.ts",
      "src/shared/runtime-types.ts",
      "src/shared/runtime-rpc-envelope.ts",
      "src/shared/ssh-types.ts",
      "src/shared/worktree-id.ts",
      "src/shared/workspace-session-schema.ts",
      "src/shared/protocol-version.ts"
    ],
    "discovered_from": "L0-project-overview",
    "topic_dir": "teach/open-ai-desktop/orca/module-shared-contracts",
    "output_path": "teach/open-ai-desktop/orca/module-shared-contracts/lessons/0001-shared-contracts-module-tour.html",
    "required_outputs": {
      "meta": [
        "teach/open-ai-desktop/orca/module-shared-contracts/MISSION.md",
        "teach/open-ai-desktop/orca/module-shared-contracts/RESOURCES.md",
        "teach/open-ai-desktop/orca/module-shared-contracts/SNAPSHOT.md"
      ],
      "lessons": [
        "teach/open-ai-desktop/orca/module-shared-contracts/lessons/0001-shared-contracts-module-tour.html"
      ],
      "reference": [
        "teach/open-ai-desktop/orca/module-shared-contracts/reference/shared-contracts-overview.html"
      ]
    },
    "lesson_manifest": [
      {
        "path": "teach/open-ai-desktop/orca/module-shared-contracts/lessons/0001-shared-contracts-module-tour.html",
        "objective": "15 分钟理解 shared 如何承担跨进程契约层",
        "estimated_minutes": 15
      }
    ],
    "new_goals_found": [
      "L3-runtime-rpc-envelope",
      "L3-worktree-id",
      "L3-workspace-session-schema"
    ],
    "retry_count": 1,
    "completed_at": "2026-07-07T17:40:25+08:00",
    "review_status": "passed",
    "review_issues": {
      "critical": [
        {
          "location": "lessons/0001-shared-contracts-module-tour.html 文件树与 isKeepaliveFrame 示例",
          "description": "初版文件树未使用 filetree 容器，且 isKeepaliveFrame 示例遗漏 _keepalive === true。",
          "resolution": "已改为 <div class=\"filetree\">，并替换为与源码一致的严格判断；复审通过。"
        }
      ],
      "important": [
        {
          "location": "reference/shared-contracts-overview.html 内部分层与 mobile 表述",
          "description": "初版内部分层/关键依赖不够显式，mobile 直接复用 shared envelope 的表述过强。",
          "resolution": "已新增“内部结构与依赖”表，并说明 mobile 镜像部分 transport 兼容逻辑。"
        }
      ],
      "minor": [
        {
          "location": "lessons/0001-shared-contracts-module-tour.html 标题",
          "description": "“三类核心文件”标题与六个文件不一致。",
          "resolution": "已改为“核心文件速览”。"
        }
      ]
    },
    "review_round": 2
  },
  {
    "id": "L2-worktree-create-flow",
    "level": "L2_vertical_slice",
    "title": "创建 Worktree 并启动 Agent 全链路",
    "parent": "L1-main-runtime",
    "status": "done",
    "depends_on": [
      "L1-main-runtime",
      "L1-main-ipc",
      "L1-renderer-shell"
    ],
    "sources": [
      "src/renderer/src/components/NewWorkspaceComposerModal.tsx",
      "src/renderer/src/hooks/useComposerState.ts",
      "src/renderer/src/lib/pending-worktree-creation.ts",
      "src/renderer/src/lib/worktree-creation-flow.ts",
      "src/renderer/src/lib/worktree-activation.ts",
      "src/renderer/src/lib/new-workspace.ts",
      "src/renderer/src/lib/ephemeral-vm-worktree-creation.ts",
      "src/renderer/src/store/slices/worktrees.ts",
      "src/preload/index.ts",
      "src/renderer/src/hooks/useIpcEvents.ts",
      "src/main/ipc/worktrees.ts",
      "src/main/ipc/worktree-remote.ts",
      "src/main/worktree-create-base.ts",
      "src/main/runtime/orca-runtime.ts",
      "src/main/git/worktree.ts",
      "src/main/runtime/rpc/methods/worktree.ts",
      "src/shared/types.ts",
      "src/shared/worktree-id.ts",
      "src/renderer/src/lib/worktree-creation-flow.test.ts",
      "src/renderer/src/store/slices/worktrees.test.ts",
      "src/main/worktree-create-base.test.ts",
      "src/main/ipc/worktrees.test.ts",
      "src/main/runtime/rpc/methods/worktree.test.ts"
    ],
    "discovered_from": "L0-project-overview",
    "topic_dir": "teach/open-ai-desktop/orca/slice-worktree-create-flow",
    "output_path": "teach/open-ai-desktop/orca/slice-worktree-create-flow/lessons/0001-worktree-create-flow.html",
    "required_outputs": {
      "meta": [
        "teach/open-ai-desktop/orca/slice-worktree-create-flow/MISSION.md",
        "teach/open-ai-desktop/orca/slice-worktree-create-flow/RESOURCES.md",
        "teach/open-ai-desktop/orca/slice-worktree-create-flow/SNAPSHOT.md"
      ],
      "lessons": [
        "teach/open-ai-desktop/orca/slice-worktree-create-flow/lessons/0001-worktree-create-flow.html"
      ],
      "reference": [
        "teach/open-ai-desktop/orca/slice-worktree-create-flow/reference/worktree-create-flow-overview.html"
      ]
    },
    "lesson_manifest": [
      {
        "path": "teach/open-ai-desktop/orca/slice-worktree-create-flow/lessons/0001-worktree-create-flow.html",
        "objective": "15 分钟内从 renderer 提交追到 Git 创建和终端交接",
        "estimated_minutes": 15
      }
    ],
    "new_goals_found": [],
    "retry_count": 1,
    "completed_at": "2026-07-07T19:08:37+08:00",
    "review_status": "conditional_pass",
    "review_issues": {
      "critical": [],
      "important": [
        {
          "location": "lessons/0001-worktree-create-flow.html、RESOURCES.md、reference/worktree-create-flow-overview.html",
          "description": "独立审查指出初版把 desktop SSH helper 写得像也负责 startup terminal，容易混淆 local IPC、desktop SSH IPC、runtime managed local/SSH 四条路径。",
          "resolution": "已拆清边界：desktop SSH helper 只创建远端 worktree 并返回 setup/default tabs；本地 helper 可直接 backend-spawn startup terminal；managed SSH runtime 在 orca-runtime.ts 包装层处理 startup/setup terminal。"
        },
        {
          "location": "RESOURCES.md 与 SNAPSHOT.md",
          "description": "独立审查指出 terminal handoff 的关键源文件缺失。",
          "resolution": "已补充 src/renderer/src/lib/worktree-activation.ts、src/renderer/src/lib/new-workspace.ts，并在参考页写入 activate、background terminal seed、ensureAgentStartupInTerminal 与 no-double-spawn 责任。"
        }
      ],
      "minor": [
        {
          "location": "reference/worktree-create-flow-overview.html 进度语义",
          "description": "初版把 fetching/creating 泛称为 main helper 事件。",
          "resolution": "已限定为 local main helper 的细分事件，并说明 SSH/runtime 可使用 indeterminate 进度。"
        },
        {
          "location": "lessons/0001-worktree-create-flow.html 范围表述",
          "description": "初版“新建 workspace 不是同步 IPC 调用”表述过宽。",
          "resolution": "已限定为 NewWorkspaceComposerModal 的 quick/background 创建路径，并在资源和笔记中保留长提交路径差异。"
        },
        {
          "location": "RESOURCES.md 与 reference/worktree-create-flow-overview.html",
          "description": "初版提到 VM provisioning 但未列源文件。",
          "resolution": "已补充 src/renderer/src/lib/ephemeral-vm-worktree-creation.ts，并标注为创建前旁支。"
        }
      ]
    },
    "review_round": 1
  },
  {
    "id": "L2-ssh-relay-session-flow",
    "level": "L2_vertical_slice",
    "title": "SSH Relay 会话保活全链路",
    "parent": "L1-cli-relay",
    "status": "done",
    "depends_on": [
      "L1-main-runtime",
      "L1-cli-relay",
      "L1-shared-contracts"
    ],
    "sources": [
      "src/main/ipc/pty.ts",
      "src/main/ipc/ssh.ts",
      "src/main/ssh/ssh-connection.ts",
      "src/main/ssh/ssh-relay-deploy.ts",
      "src/main/ssh/ssh-relay-deploy-helpers.ts",
      "src/main/ssh/ssh-relay-session.ts",
      "src/relay/protocol.ts",
      "src/relay/relay.ts",
      "src/relay/relay-handshake.ts",
      "src/relay/pty-handler.ts",
      "src/relay/workspace-session-handler.ts",
      "src/renderer/src/App.tsx",
      "src/renderer/src/store/slices/terminals.ts",
      "src/renderer/src/components/terminal-pane/pty-connection.ts",
      "src/shared/ssh-types.ts",
      "src/main/ssh/ssh-channel-multiplexer.test.ts",
      "src/main/ssh/ssh-relay-cross-version-isolation.test.ts",
      "src/main/ssh/ssh-relay-deploy.test.ts",
      "src/main/ssh/ssh-relay-session.test.ts",
      "src/relay/relay-handshake-roundtrip.test.ts",
      "src/renderer/src/app-startup-routing.test.ts",
      "src/renderer/src/components/terminal-pane/pty-connection.test.ts"
    ],
    "discovered_from": "L0-project-overview",
    "topic_dir": "teach/open-ai-desktop/orca/slice-ssh-relay-session-flow",
    "output_path": "teach/open-ai-desktop/orca/slice-ssh-relay-session-flow/lessons/0001-flow-map.html",
    "required_outputs": {
      "meta": [
        "teach/open-ai-desktop/orca/slice-ssh-relay-session-flow/MISSION.md",
        "teach/open-ai-desktop/orca/slice-ssh-relay-session-flow/RESOURCES.md",
        "teach/open-ai-desktop/orca/slice-ssh-relay-session-flow/SNAPSHOT.md"
      ],
      "lessons": [
        "teach/open-ai-desktop/orca/slice-ssh-relay-session-flow/lessons/0001-flow-map.html"
      ],
      "reference": [
        "teach/open-ai-desktop/orca/slice-ssh-relay-session-flow/reference/ssh-relay-session-flow-map.html"
      ]
    },
    "lesson_manifest": [
      {
        "path": "teach/open-ai-desktop/orca/slice-ssh-relay-session-flow/lessons/0001-flow-map.html",
        "objective": "15 分钟内从 SSH connect 追到 detached relay、grace socket 和 PTY reattach",
        "estimated_minutes": 15
      }
    ],
    "new_goals_found": [],
    "retry_count": 1,
    "completed_at": "2026-07-07T19:36:31+08:00",
    "review_status": "conditional_pass",
    "review_issues": {
      "critical": [],
      "important": [
        {
          "location": "reference/ssh-relay-session-flow-map.html 版本握手和 sentinel",
          "description": "独立审查指出初版把 version mismatch 写成一律 terminal relay error，忽略已有 socket `--connect` 失败可被 deploy path 当作 stale socket/pipe 恢复并 fresh launch。",
          "resolution": "已拆成两层：bridge exit 42 会映射为 RelayVersionMismatchError；已有 socket 连接失败先走 stale socket/pipe 恢复；只有最终抛到 SshRelaySession 的 version mismatch 才跳过普通 relay-lost backoff。"
        }
      ],
      "minor": [
        {
          "location": "RESOURCES.md",
          "description": "初版把 passphrase/timeout target 的 deferred 分类归到 terminals.ts。",
          "resolution": "已改为 App.tsx 负责 passphrase target 与 15 秒超时 target 分类，terminals.ts 负责保存未 connected SSH repo 的 deferred session id。"
        },
        {
          "location": "reference/ssh-relay-session-flow-map.html grace 语义",
          "description": "初版把 shared contract 写成负责 clamp，边界不清。",
          "resolution": "已说明 shared 只定义 0/min/max/default 与字段语义；main session/deploy 路径负责 clamp，远端 relay 只接收已归一化的非负秒数。"
        }
      ]
    },
    "review_round": 1
  },
  {
    "id": "L2-orca-cli-command-flow",
    "level": "L2_vertical_slice",
    "title": "Orca CLI 命令执行全链路",
    "parent": "L1-cli-relay",
    "status": "done",
    "depends_on": [
      "L1-cli-relay",
      "L1-shared-contracts"
    ],
    "sources": [
      "src/cli/index.ts",
      "src/cli/args.ts",
      "src/cli/dispatch.ts",
      "src/cli/runtime-client.ts",
      "src/cli/specs"
    ],
    "discovered_from": "L0-project-overview",
    "topic_dir": "teach/open-ai-desktop/orca/slice-orca-cli-command-flow",
    "output_path": "teach/open-ai-desktop/orca/slice-orca-cli-command-flow/lessons/0001-flow-map.html",
    "required_outputs": {
      "meta": [
        "teach/open-ai-desktop/orca/slice-orca-cli-command-flow/MISSION.md",
        "teach/open-ai-desktop/orca/slice-orca-cli-command-flow/RESOURCES.md",
        "teach/open-ai-desktop/orca/slice-orca-cli-command-flow/SNAPSHOT.md"
      ],
      "lessons": [
        "teach/open-ai-desktop/orca/slice-orca-cli-command-flow/lessons/0001-flow-map.html"
      ],
      "reference": [
        "teach/open-ai-desktop/orca/slice-orca-cli-command-flow/reference/orca-cli-command-flow-map.html"
      ]
    },
    "lesson_manifest": [
      {
        "path": "teach/open-ai-desktop/orca/slice-orca-cli-command-flow/lessons/0001-flow-map.html",
        "objective": "15 分钟内从 CLI argv 追到 RuntimeClient 与 main runtime RPC method",
        "estimated_minutes": 15
      }
    ],
    "new_goals_found": [],
    "retry_count": 1,
    "completed_at": "2026-07-07T20:06:50+08:00",
    "review_status": "conditional_pass",
    "review_issues": {
      "critical": [],
      "important": [
        {
          "location": "lessons/0001-flow-map.html 检索练习",
          "description": "独立审查指出初版把远程 `worktree current` 写成可通过显式 server-side selector 解决，但该 command spec 没有 selector flag，handler 固定解析 cwd。",
          "resolution": "已改为说明 remote 下 `worktree current` 应被拒绝；需要显式 selector 时改用 `worktree show --worktree id:<id>` 等接受 selector 的命令。"
        },
        {
          "location": "RESOURCES.md / reference/orca-cli-command-flow-map.html",
          "description": "独立审查指出只列 `src/cli/specs/index.ts` 不足以追具体命令 allowed flags。",
          "resolution": "已补充 `src/cli/specs/core.ts`、`serve.ts`、`browser-basic.ts`、`browser-advanced.ts`、`orchestration.ts`，并重建快照。"
        },
        {
          "location": "RESOURCES.md / reference/orca-cli-command-flow-map.html 测试护栏",
          "description": "独立审查指出遗漏与 orchestration heartbeat/timeout 断言直接对应的测试资源。",
          "resolution": "已补充 `src/cli/handlers/orchestration.test.ts` 与 `src/main/runtime/orchestration-cli-subprocess.test.ts`。"
        },
        {
          "location": "reference/orca-cli-command-flow-map.html main runtime RPC 边界",
          "description": "独立审查指出 `orchestration.ask` 是阻塞 RPC 且有 CLI per-call timeout override，但不属于 server long-poll keepalive/cap 分类。",
          "resolution": "已补充 `terminal.wait` / `orchestration.check --wait` 与 `orchestration.ask` 的分类差异。"
        }
      ],
      "minor": []
    },
    "review_round": 1
  },
  {
    "id": "L2-mobile-pairing-flow",
    "level": "L2_vertical_slice",
    "title": "移动端配对与会话恢复全链路",
    "parent": "L1-mobile-companion",
    "status": "done",
    "depends_on": [
      "L1-main-runtime",
      "L1-mobile-companion",
      "L1-shared-contracts"
    ],
    "sources": [
      "src/renderer/src/components/settings/MobilePane.tsx",
      "src/main/ipc/mobile.ts",
      "src/main/runtime/runtime-rpc.ts",
      "src/main/runtime/device-registry.ts",
      "mobile/app/pair.tsx",
      "mobile/app/pair-scan.tsx",
      "mobile/app/pair-confirm.tsx",
      "mobile/src/transport/pairing.ts",
      "mobile/src/transport/host-store.ts",
      "mobile/src/transport/rpc-client.ts",
      "mobile/src/transport/client-context.tsx",
      "mobile/app/index.tsx",
      "src/main/runtime/mobile-pairing-files.ts",
      "src/shared/pairing.ts"
    ],
    "discovered_from": "L0-project-overview",
    "topic_dir": "teach/open-ai-desktop/orca/slice-mobile-pairing-flow",
    "output_path": "teach/open-ai-desktop/orca/slice-mobile-pairing-flow/lessons/0001-flow-map.html",
    "required_outputs": {
      "meta": [
        "teach/open-ai-desktop/orca/slice-mobile-pairing-flow/MISSION.md",
        "teach/open-ai-desktop/orca/slice-mobile-pairing-flow/RESOURCES.md",
        "teach/open-ai-desktop/orca/slice-mobile-pairing-flow/SNAPSHOT.md"
      ],
      "lessons": [
        "teach/open-ai-desktop/orca/slice-mobile-pairing-flow/lessons/0001-flow-map.html"
      ],
      "reference": [
        "teach/open-ai-desktop/orca/slice-mobile-pairing-flow/reference/mobile-pairing-flow-map.html"
      ]
    },
    "lesson_manifest": [
      {
        "path": "teach/open-ai-desktop/orca/slice-mobile-pairing-flow/lessons/0001-flow-map.html",
        "objective": "15 分钟内把桌面 QR、E2EE 握手、host 保存和 Resume 恢复串成一条链路",
        "estimated_minutes": 15
      }
    ],
    "new_goals_found": [],
    "retry_count": 1,
    "completed_at": "2026-07-07T20:34:09+08:00",
    "review_status": "conditional_pass",
    "review_issues": {
      "critical": [],
      "important": [
        {
          "location": "RESOURCES.md / reference/mobile-pairing-flow-map.html",
          "description": "独立审查指出 mobile/README.md 当前仍写 QR 编码 TLS fingerprint，不能作为 pairing payload 的权威来源。",
          "resolution": "已补充说明 mobile/README.md 仅用于开发环境和网络要求参考；QR payload 以 src/shared/pairing.ts 与 runtime createPairingOffer() 为准。"
        },
        {
          "location": "lessons/0001-flow-map.html / reference/mobile-pairing-flow-map.html",
          "description": "独立审查指出初版容易把桌面/shared payload 中的 optional scope 与 mobile 本地 PairingOfferSchema 混为一谈。",
          "resolution": "已明确 shared payload 当前包含 optional scope；mobile/src/transport/types.ts 的 PairingOfferSchema 只保留 v、endpoint、deviceToken、publicKeyB64，mobile 授权以 token registry、allowlist 和 status.get.deviceScope 为准。"
        }
      ],
      "minor": [
        {
          "location": "SNAPSHOT.md",
          "description": "独立审查指出资源页列出的 mobile/README.md、mobile/src/transport/types.ts、mobile/src/transport/e2ee.ts、mobile/app/h/[hostId]/index.tsx 未进入快照引用。",
          "resolution": "已在参考页补充这些文件的实际引用并重新生成 SNAPSHOT.md，快照引用源文件数更新为 40。"
        },
        {
          "location": "NOTES.md / reference/mobile-pairing-flow-map.html Resume 说明",
          "description": "独立审查指出初版少了多 host 场景排序边界。",
          "resolution": "已补充跨 host 先按 host lastConnected 遍历；desktop active/lastOutputAt 只是在单个 host worktree 列表内的 fallback。"
        },
        {
          "location": "lessons/0001-flow-map.html 保存失败说明",
          "description": "独立审查指出初版把源码英文 UI 文案写成带引号的中文意译，容易误导检索。",
          "resolution": "已改为源码中的英文文案 `Pairing succeeded but couldn't save the host`。"
        }
      ]
    },
    "review_round": 1
  },
  {
    "id": "L4-relay-reconnect",
    "level": "L4_deep_dive",
    "title": "Relay 断线重连与 Grace Socket 机制",
    "parent": "L1-cli-relay",
    "status": "done",
    "depends_on": [
      "L1-cli-relay"
    ],
    "sources": [
      "src/main/ipc/ssh.test.ts",
      "src/main/ipc/ssh.ts",
      "src/main/ssh/relay-protocol.test.ts",
      "src/main/ssh/relay-protocol.ts",
      "src/main/ssh/ssh-channel-multiplexer.test.ts",
      "src/main/ssh/ssh-channel-multiplexer.ts",
      "src/main/ssh/ssh-relay-cross-version-isolation.test.ts",
      "src/main/ssh/ssh-relay-deploy-helpers.test.ts",
      "src/main/ssh/ssh-relay-deploy-helpers.ts",
      "src/main/ssh/ssh-relay-deploy.test.ts",
      "src/main/ssh/ssh-relay-deploy.ts",
      "src/main/ssh/ssh-relay-endpoints.ts",
      "src/main/ssh/ssh-relay-handshake-mismatch.ts",
      "src/main/ssh/ssh-relay-instance-id.ts",
      "src/main/ssh/ssh-relay-session-terminal-error.test.ts",
      "src/main/ssh/ssh-relay-session.test.ts",
      "src/main/ssh/ssh-relay-session.ts",
      "src/main/ssh/ssh-relay-version-mismatch-error.ts",
      "src/relay/dispatcher.test.ts",
      "src/relay/dispatcher.ts",
      "src/relay/protocol-handshake.test.ts",
      "src/relay/protocol.ts",
      "src/relay/pty-handler.test.ts",
      "src/relay/pty-handler.ts",
      "src/relay/relay-handshake-roundtrip.test.ts",
      "src/relay/relay-handshake.ts",
      "src/relay/relay.ts",
      "src/relay/subprocess.test.ts",
      "src/shared/ssh-types.ts"
    ],
    "discovered_from": "L0-project-overview",
    "topic_dir": "teach/open-ai-desktop/orca/deep-dive-relay-reconnect",
    "output_path": "teach/open-ai-desktop/orca/deep-dive-relay-reconnect/lessons/0001-problem-frame.html",
    "required_outputs": {
      "meta": [
        "teach/open-ai-desktop/orca/deep-dive-relay-reconnect/MISSION.md",
        "teach/open-ai-desktop/orca/deep-dive-relay-reconnect/RESOURCES.md",
        "teach/open-ai-desktop/orca/deep-dive-relay-reconnect/SNAPSHOT.md"
      ],
      "lessons": [
        "teach/open-ai-desktop/orca/deep-dive-relay-reconnect/lessons/0001-problem-frame.html"
      ],
      "reference": [
        "teach/open-ai-desktop/orca/deep-dive-relay-reconnect/reference/relay-reconnect-notes.html"
      ]
    },
    "lesson_manifest": [
      {
        "path": "teach/open-ai-desktop/orca/deep-dive-relay-reconnect/lessons/0001-problem-frame.html",
        "objective": "15 分钟内把一次 SSH/relay 断线恢复归类到部署层、socket 接入层或 dispatcher client 层",
        "estimated_minutes": 15
      }
    ],
    "new_goals_found": [],
    "retry_count": 1,
    "completed_at": "2026-07-07T21:01:40+08:00",
    "review_status": "conditional_pass",
    "review_issues": {
      "critical": [],
      "important": [
        {
          "location": "lessons/0001-problem-frame.html 检索练习答案",
          "description": "独立审查指出初版把 POSIX `ALIVE` 描述为端点可连接，但源码中 POSIX probe 只是 `test -S`，只能证明 socket inode 存在。",
          "resolution": "已改为区分 POSIX `ALIVE` 与 Windows `READY`；两者都还需要 `--connect`、handshake 和 sentinel 才能判定可用。"
        }
      ],
      "minor": [
        {
          "location": "RESOURCES.md / SNAPSHOT.md / reference/relay-reconnect-notes.html",
          "description": "独立审查指出 `waitForSentinel()` exit 42 映射和 empty detached startup grace 的测试引用不完整。",
          "resolution": "已补充 `src/main/ssh/ssh-relay-deploy-helpers.test.ts` 与 `src/relay/subprocess.test.ts`，并重新生成 SNAPSHOT.md，引用数更新为 29。"
        },
        {
          "location": "reference/relay-reconnect-notes.html protocol-handshake 测试说明",
          "description": "独立审查指出“非 handshake payload 拒绝”表述过宽。",
          "resolution": "已收窄为 handshake frame 编码/解析、mismatch message、未知 handshake type 拒绝和 Handshake/Regular/KeepAlive 类型区分。"
        },
        {
          "location": "teach/open-ai-desktop/orca/index.md",
          "description": "独立审查指出项目级索引未收录 `./deep-dive-relay-reconnect/`。",
          "resolution": "已新增 Relay 重连与 Grace Socket 索引条目。"
        }
      ]
    },
    "review_round": 1
  }
]
